pypermm/__init__.py
pypermm/asa.py
pypermm/atoms.py
pypermm/constants.py
pypermm/dipole_lib.json
pypermm/dipoles.py
pypermm/math_utils.py
pypermm/membrane.py
pypermm/orientation.py
pypermm/permeability.py
pypermm/py.typed
pypermm/pypermm.py
pypermm-0.0.4.dist-info/licenses/LICENSE
pypermm-0.0.4.dist-info/METADATA
pypermm-0.0.4.dist-info/WHEEL
pypermm-0.0.4.dist-info/top_level.txt
pypermm-0.0.4.dist-info/RECORD
