Metadata-Version: 2.4
Name: pypermm
Version: 0.0.4
Summary: pypermm
Author: Corin Wagen
License-Expression: MIT
Requires-Python: >=3.12
License-File: LICENSE
Requires-Dist: numpy==2.*
Dynamic: license-file
